{"generated": "2026-05-04", "total_screened": 3, "total_passed": 2, "total_rejected": 1, "companies": [{"ticker": "NNDM", "name": "Nano Dimension Ltd.", "market_cap": 399636064, "sector": "Technology", "industry": "Computer Hardware", "market_tag": "Computer Hardware", "cash": 457823008, "operating_cashflow": -101284000, "runway_months": 54.2, "revenue": 102437000, "revenue_growth": 113.5, "shares_outstanding": 207986287, "insider_held_pct": 5.5, "sbc_to_revenue": 0.0, "has_reverse_split": false, "red_flags": [], "red_flag_count": 0, "fcf": -43309376, "fcf_yield": -10.84, "book_value": 2.67, "price_to_book": 0.71, "profit_margin": -286.3, "operating_margin": -50.9, "roe": -14.2, "debt_to_equity": 5.9, "gross_margin": 33.5, "current_ratio": 10.02, "dividend_yield": null, "shares_change_yoy": -4.2, "shares_change_3yr": -20.0, "has_positive_fcf": false, "low_debt": true, "high_roe": false, "wide_moat": false, "buffett_quality": false, "is_buying_back": true, "is_diluting": false, "is_cannibal": true, "fcf_trend": "volatile", "fcf_cagr_3yr": null, "fcf_consecutive_positive": 0, "fcf_history": [{"year": 2022, "fcf": -101442000}, {"year": 2023, "fcf": -79279000}, {"year": 2024, "fcf": -21828000}, {"year": 2025, "fcf": -102348000}], "health_chart": {"years": [2022, 2023, 2024, 2025], "revenue": [43.6, 56.3, 57.8, 102.4], "net_income": [-227.4, -56.0, -98.8, -293.3], "fcf": [-101.4, -79.3, -21.8, -102.3], "total_debt": [18.0, 13.8, 3.8, 9.2], "roic": [-27.2, -18.0, -16.2, -23.9], "gross_margin": [32.2, 46.3, 43.1, 33.5], "shares": [258.6, 206.6, 215.8, 206.8], "fcf_yield": [-15.5, -17.2, -4.4, -28.6]}}, {"ticker": "PUBM", "name": "PubMatic, Inc.", "market_cap": 485905600, "sector": "Technology", "industry": "Software - Application", "market_tag": "Application Software", "cash": 145518000, "operating_cashflow": 81059000, "runway_months": 999, "revenue": 282926016, "revenue_growth": -6.4, "shares_outstanding": 38411753, "insider_held_pct": 6.9, "sbc_to_revenue": 33.8, "has_reverse_split": false, "red_flags": [], "red_flag_count": 0, "fcf": 50818876, "fcf_yield": 10.46, "book_value": 5.6, "price_to_book": 1.83, "profit_margin": -5.1, "operating_margin": 11.8, "roe": -5.4, "debt_to_equity": 16.8, "gross_margin": 63.6, "current_ratio": 1.39, "dividend_yield": null, "shares_change_yoy": -2.5, "shares_change_3yr": -11.0, "has_positive_fcf": true, "low_debt": true, "high_roe": false, "wide_moat": false, "buffett_quality": false, "is_buying_back": true, "is_diluting": false, "is_cannibal": true, "fcf_trend": "growing", "fcf_cagr_3yr": 6.4, "fcf_consecutive_positive": 4, "fcf_history": [{"year": 2022, "fcf": 38319000}, {"year": 2023, "fcf": 52833000}, {"year": 2024, "fcf": 34897000}, {"year": 2025, "fcf": 46203000}], "health_chart": {"years": [2022, 2023, 2024, 2025], "revenue": [256.4, 267.0, 291.3, 282.9], "net_income": [28.7, 8.9, 12.5, -14.5], "fcf": [38.3, 52.8, 34.9, 46.2], "total_debt": [26.6, 21.8, 45.4, 43.9], "roic": [12.6, 0.7, 1.2, -9.7], "gross_margin": [68.2, 62.8, 65.3, 63.6], "shares": [52.7, 50.2, 48.1, 46.9], "fcf_yield": [5.1, 7.0, 5.2, 11.8]}}], "rejected": [{"ticker": "KULR", "reason": "Low score with red flags"}], "market_tags": {"Computer Hardware": ["NNDM"], "Application Software": ["PUBM"]}}